biocpd/__init__.py
biocpd/affine_registration.py
biocpd/atlas_registration.py
biocpd/constrained_deformable_registration.py
biocpd/deformable_registration.py
biocpd/emregistration.py
biocpd/rigid_registration.py
biocpd/utility.py
biocpd-0.1.1.dist-info/METADATA
biocpd-0.1.1.dist-info/WHEEL
biocpd-0.1.1.dist-info/top_level.txt
biocpd-0.1.1.dist-info/RECORD
