Metadata-Version: 2.4
Name: biocpd
Version: 0.1.1
Summary: Coherent Point Drift variants (rigid, affine, deformable, PCA/SSM) in NumPy/SciPy
Home-page: https://github.com/agporto/biocpd
Author: Arthur Porto
Author-email: agporto@gmail.com
License: MIT
Keywords: point cloud registration CPD
Classifier: Development Status :: 3 - Alpha
Classifier: License :: OSI Approved :: MIT License
Classifier: Programming Language :: Python :: 3
Classifier: Topic :: Scientific/Engineering
Requires-Dist: numpy
Requires-Dist: scipy
Requires-Dist: scikit-learn
Requires-Dist: matplotlib
Dynamic: author
Dynamic: author-email
Dynamic: classifier
Dynamic: description
Dynamic: description-content-type
Dynamic: home-page
Dynamic: keywords
Dynamic: license
Dynamic: requires-dist
Dynamic: summary
